pclog/__init__.py
pclog/__main__.py
pclog/core.py
pclog/example.py
pclog/formatters.py
pclog/hooks.py
pclog/processors.py
pclog/pyg.py
pclog/settings.py
pclog/conf/default.conf
pclog/conf/meta.ini
pclog-0.1.0.dist-info/LICENSE
pclog-0.1.0.dist-info/METADATA
pclog-0.1.0.dist-info/WHEEL
pclog-0.1.0.dist-info/top_level.txt
pclog-0.1.0.dist-info/RECORD
